[
    {
        "id": 0,
        "timestamp": 0.0,
        "hit_pos": 7,
        "hold_pos": 3,
        "note_width": [
            6,
            7,
            8,
            9
        ],
        "description": "s_start",
        "command": "tap",
        "hitline": 0,
        "execution": "t"
    },
    {
        "id": 1,
        "timestamp": 1.295,
        "hit_pos": 9,
        "hold_pos": 4,
        "note_width": [
            8,
            9,
            10,
            11
        ],
        "description": "s_end",
        "command": "virtual_release",
        "hitline": 1,
        "execution": "r"
    },
    {
        "id": 1.5,
        "timestamp": 1.335,
        "hit_pos": -1,
        "hold_pos": 4,
        "note_width": [],
        "description": "",
        "command": "virtual_resume",
        "hitline": 2,
        "execution": "h"
    },
    {
        "id": 2,
        "timestamp": 1.727,
        "hit_pos": 3,
        "hold_pos": 2,
        "note_width": [
            2,
            3,
            4,
            5
        ],
        "description": "s_start",
        "command": "tap",
        "hitline": 0,
        "execution": "t"
    },
    {
        "id": 5,
        "timestamp": 4.748,
        "hit_pos": 2,
        "hold_pos": 0,
        "note_width": [
            0,
            1,
            2,
            3
        ],
        "description": "s_end",
        "command": "virtual_release",
        "hitline": 1,
        "execution": "r"
    },
    {
        "id": 5.5,
        "timestamp": 4.788,
        "hit_pos": -1,
        "hold_pos": 0,
        "note_width": [],
        "description": "",
        "command": "virtual_resume",
        "hitline": 2,
        "execution": "h"
    },
    {
        "id": 6,
        "timestamp": 5.18,
        "hit_pos": 9,
        "hold_pos": 5,
        "note_width": [
            8,
            9,
            10,
            11
        ],
        "description": "s_start",
        "command": "tap",
        "hitline": 0,
        "execution": "t"
    },
    {
        "id": 7,
        "timestamp": 6.043,
        "hit_pos": 7,
        "hold_pos": 3,
        "note_width": [
            6,
            7,
            8,
            9
        ],
        "description": "s_end",
        "command": "virtual_release",
        "hitline": 1,
        "execution": "r"
    },
    {
        "id": 7.5,
        "timestamp": 6.083,
        "hit_pos": -1,
        "hold_pos": 3,
        "note_width": [],
        "description": "",
        "command": "virtual_resume",
        "hitline": 2,
        "execution": "h"
    },
    {
        "id": 8,
        "timestamp": 6.906,
        "hit_pos": 1,
        "hold_pos": 0,
        "note_width": [
            0,
            1,
            2
        ],
        "description": "c_tap",
        "command": "tap",
        "hitline": 0,
        "execution": "t"
    },
    {
        "id": 9,
        "timestamp": 6.906,
        "hit_pos": 9,
        "hold_pos": 5,
        "note_width": [
            9,
            10,
            11
        ],
        "description": "c_tap",
        "command": "tap",
        "hitline": 0,
        "execution": "t"
    },
    {
        "id": 10,
        "timestamp": 7.338,
        "hit_pos": 1,
        "hold_pos": 0,
        "note_width": [
            0,
            1,
            2
        ],
        "description": "tap",
        "command": "tap",
        "hitline": 0,
        "execution": "t"
    },
    {
        "id": 11,
        "timestamp": 7.77,
        "hit_pos": 7,
        "hold_pos": 3,
        "note_width": [
            6,
            7,
            8
        ],
        "description": "tap",
        "command": "tap",
        "hitline": 0,
        "execution": "t"
    },
    {
        "id": 12,
        "timestamp": 8.201,
        "hit_pos": 7,
        "hold_pos": 3,
        "note_width": [
            6,
            7,
            8
        ],
        "description": "tap",
        "command": "tap",
        "hitline": 0,
        "execution": "t"
    },
    {
        "id": 13,
        "timestamp": 8.633,
        "hit_pos": 4,
        "hold_pos": 1,
        "note_width": [
            3,
            4,
            5
        ],
        "description": "tap",
        "command": "tap",
        "hitline": 0,
        "execution": "t"
    },
    {
        "id": 14,
        "timestamp": 9.065,
        "hit_pos": 4,
        "hold_pos": 2,
        "note_width": [
            3,
            4,
            5
        ],
        "description": "tap",
        "command": "tap",
        "hitline": 0,
        "execution": "t"
    },
    {
        "id": 15,
        "timestamp": 9.496,
        "hit_pos": 9,
        "hold_pos": 4,
        "note_width": [
            9,
            10,
            11
        ],
        "description": "tap",
        "command": "tap",
        "hitline": 0,
        "execution": "t"
    },
    {
        "id": 16,
        "timestamp": 9.928,
        "hit_pos": 9,
        "hold_pos": 5,
        "note_width": [
            9,
            10,
            11
        ],
        "description": "tap",
        "command": "tap",
        "hitline": 0,
        "execution": "t"
    },
    {
        "id": 17,
        "timestamp": 10.36,
        "hit_pos": 1,
        "hold_pos": 0,
        "note_width": [
            0,
            1,
            2
        ],
        "description": "tap",
        "command": "tap",
        "hitline": 0,
        "execution": "t"
    },
    {
        "id": 18,
        "timestamp": 10.791,
        "hit_pos": 1,
        "hold_pos": 0,
        "note_width": [
            0,
            1,
            2
        ],
        "description": "tap",
        "command": "tap",
        "hitline": 0,
        "execution": "t"
    },
    {
        "id": 19,
        "timestamp": 11.223,
        "hit_pos": 7,
        "hold_pos": 3,
        "note_width": [
            6,
            7,
            8
        ],
        "description": "tap",
        "command": "tap",
        "hitline": 0,
        "execution": "t"
    },
    {
        "id": 20,
        "timestamp": 11.655,
        "hit_pos": 7,
        "hold_pos": 3,
        "note_width": [
            6,
            7,
            8
        ],
        "description": "tap",
        "command": "tap",
        "hitline": 0,
        "execution": "t"
    },
    {
        "id": 21,
        "timestamp": 12.086,
        "hit_pos": 1,
        "hold_pos": 0,
        "note_width": [
            0,
            1,
            2
        ],
        "description": "tap",
        "command": "tap",
        "hitline": 0,
        "execution": "t"
    },
    {
        "id": 22,
        "timestamp": 12.518,
        "hit_pos": 4,
        "hold_pos": 2,
        "note_width": [
            3,
            4,
            5
        ],
        "description": "tap",
        "command": "tap",
        "hitline": 0,
        "execution": "t"
    },
    {
        "id": 23,
        "timestamp": 12.95,
        "hit_pos": 7,
        "hold_pos": 3,
        "note_width": [
            6,
            7,
            8
        ],
        "description": "tap",
        "command": "tap",
        "hitline": 0,
        "execution": "t"
    },
    {
        "id": 24,
        "timestamp": 13.381,
        "hit_pos": 9,
        "hold_pos": 5,
        "note_width": [
            9,
            10,
            11
        ],
        "description": "tap",
        "command": "tap",
        "hitline": 0,
        "execution": "t"
    },
    {
        "id": 25,
        "timestamp": 13.813,
        "hit_pos": 1,
        "hold_pos": 0,
        "note_width": [
            0,
            1,
            2
        ],
        "description": "tap",
        "command": "tap",
        "hitline": 0,
        "execution": "t"
    },
    {
        "id": 26,
        "timestamp": 14.245,
        "hit_pos": 1,
        "hold_pos": 0,
        "note_width": [
            0,
            1,
            2
        ],
        "description": "tap",
        "command": "tap",
        "hitline": 0,
        "execution": "t"
    },
    {
        "id": 27,
        "timestamp": 14.676,
        "hit_pos": 7,
        "hold_pos": 3,
        "note_width": [
            6,
            7,
            8
        ],
        "description": "tap",
        "command": "tap",
        "hitline": 0,
        "execution": "t"
    },
    {
        "id": 28,
        "timestamp": 15.108,
        "hit_pos": 7,
        "hold_pos": 3,
        "note_width": [
            6,
            7,
            8
        ],
        "description": "tap",
        "command": "tap",
        "hitline": 0,
        "execution": "t"
    },
    {
        "id": 29,
        "timestamp": 15.54,
        "hit_pos": 4,
        "hold_pos": 1,
        "note_width": [
            3,
            4,
            5
        ],
        "description": "tap",
        "command": "tap",
        "hitline": 0,
        "execution": "t"
    },
    {
        "id": 30,
        "timestamp": 15.971,
        "hit_pos": 4,
        "hold_pos": 2,
        "note_width": [
            3,
            4,
            5
        ],
        "description": "tap",
        "command": "tap",
        "hitline": 0,
        "execution": "t"
    },
    {
        "id": 31,
        "timestamp": 16.403,
        "hit_pos": 9,
        "hold_pos": 4,
        "note_width": [
            9,
            10,
            11
        ],
        "description": "tap",
        "command": "tap",
        "hitline": 0,
        "execution": "t"
    },
    {
        "id": 32,
        "timestamp": 16.835,
        "hit_pos": 9,
        "hold_pos": 5,
        "note_width": [
            9,
            10,
            11
        ],
        "description": "tap",
        "command": "tap",
        "hitline": 0,
        "execution": "t"
    },
    {
        "id": 33,
        "timestamp": 17.266,
        "hit_pos": 1,
        "hold_pos": 0,
        "note_width": [
            0,
            1,
            2
        ],
        "description": "tap",
        "command": "tap",
        "hitline": 0,
        "execution": "t"
    },
    {
        "id": 34,
        "timestamp": 17.698,
        "hit_pos": 4,
        "hold_pos": 2,
        "note_width": [
            3,
            4,
            5
        ],
        "description": "tap",
        "command": "tap",
        "hitline": 0,
        "execution": "t"
    },
    {
        "id": 35,
        "timestamp": 18.129,
        "hit_pos": 7,
        "hold_pos": 3,
        "note_width": [
            6,
            7,
            8
        ],
        "description": "tap",
        "command": "tap",
        "hitline": 0,
        "execution": "t"
    },
    {
        "id": 36,
        "timestamp": 18.561,
        "hit_pos": 9,
        "hold_pos": 5,
        "note_width": [
            9,
            10,
            11
        ],
        "description": "tap",
        "command": "tap",
        "hitline": 0,
        "execution": "t"
    },
    {
        "id": 37,
        "timestamp": 18.993,
        "hit_pos": 1,
        "hold_pos": 0,
        "note_width": [
            0,
            1,
            2
        ],
        "description": "c_tap",
        "command": "tap",
        "hitline": 0,
        "execution": "t"
    },
    {
        "id": 38,
        "timestamp": 18.993,
        "hit_pos": 7,
        "hold_pos": 3,
        "note_width": [
            6,
            7,
            8
        ],
        "description": "c_tap",
        "command": "tap",
        "hitline": 0,
        "execution": "t"
    },
    {
        "id": 39,
        "timestamp": 19.424,
        "hit_pos": 9,
        "hold_pos": 5,
        "note_width": [
            9,
            10,
            11
        ],
        "description": "c_tap",
        "command": "tap",
        "hitline": 0,
        "execution": "t"
    },
    {
        "id": 40,
        "timestamp": 19.64,
        "hit_pos": 4,
        "hold_pos": 2,
        "note_width": [
            3,
            4,
            5
        ],
        "description": "c_tap",
        "command": "tap",
        "hitline": 0,
        "execution": "t"
    },
    {
        "id": 41,
        "timestamp": 20.072,
        "hit_pos": 7,
        "hold_pos": 3,
        "note_width": [
            6,
            7,
            8
        ],
        "description": "c_tap",
        "command": "tap",
        "hitline": 0,
        "execution": "t"
    },
    {
        "id": 42,
        "timestamp": 20.288,
        "hit_pos": 1,
        "hold_pos": 0,
        "note_width": [
            0,
            1,
            2
        ],
        "description": "s_start",
        "command": "tap",
        "hitline": 0,
        "execution": "t"
    },
    {
        "id": 43,
        "timestamp": 20.765,
        "hit_pos": 4,
        "hold_pos": 2,
        "note_width": [
            3,
            4,
            5
        ],
        "description": "s_endfl_up",
        "command": "endflick",
        "hitline": 0,
        "execution": "f"
    },
    {
        "id": 44,
        "timestamp": 21.367,
        "hit_pos": 7,
        "hold_pos": 3,
        "note_width": [
            6,
            7,
            8
        ],
        "description": "tap",
        "command": "tap",
        "hitline": 0,
        "execution": "t"
    },
    {
        "id": 45,
        "timestamp": 21.583,
        "hit_pos": 1,
        "hold_pos": 0,
        "note_width": [
            0,
            1,
            2
        ],
        "description": "tap",
        "command": "tap",
        "hitline": 0,
        "execution": "t"
    },
    {
        "id": 46,
        "timestamp": 21.799,
        "hit_pos": 9,
        "hold_pos": 4,
        "note_width": [
            9,
            10,
            11
        ],
        "description": "tap",
        "command": "tap",
        "hitline": 0,
        "execution": "t"
    },
    {
        "id": 47,
        "timestamp": 22.014,
        "hit_pos": 4,
        "hold_pos": 2,
        "note_width": [
            3,
            4,
            5
        ],
        "description": "s_start",
        "command": "tap",
        "hitline": 0,
        "execution": "t"
    },
    {
        "id": 49,
        "timestamp": 22.446,
        "hit_pos": 1,
        "hold_pos": 0,
        "note_width": [
            0,
            1,
            2
        ],
        "description": "s_end",
        "command": "virtual_release",
        "hitline": 2,
        "execution": "r"
    },
    {
        "id": 49.5,
        "timestamp": 22.486,
        "hit_pos": -1,
        "hold_pos": 0,
        "note_width": [],
        "description": "",
        "command": "virtual_resume",
        "hitline": 1,
        "execution": "h"
    },
    {
        "id": 50,
        "timestamp": 23.094,
        "hit_pos": 4,
        "hold_pos": 2,
        "note_width": [
            3,
            4,
            5
        ],
        "description": "tap",
        "command": "tap",
        "hitline": 0,
        "execution": "t"
    },
    {
        "id": 51,
        "timestamp": 23.309,
        "hit_pos": 9,
        "hold_pos": 5,
        "note_width": [
            9,
            10,
            11
        ],
        "description": "tap",
        "command": "tap",
        "hitline": 0,
        "execution": "t"
    },
    {
        "id": 52,
        "timestamp": 23.525,
        "hit_pos": 1,
        "hold_pos": 0,
        "note_width": [
            0,
            1,
            2
        ],
        "description": "tap",
        "command": "tap",
        "hitline": 0,
        "execution": "t"
    },
    {
        "id": 53,
        "timestamp": 23.741,
        "hit_pos": 7,
        "hold_pos": 3,
        "note_width": [
            6,
            7,
            8
        ],
        "description": "s_start",
        "command": "tap",
        "hitline": 0,
        "execution": "t"
    },
    {
        "id": 55,
        "timestamp": 24.173,
        "hit_pos": 9,
        "hold_pos": 5,
        "note_width": [
            9,
            10,
            11
        ],
        "description": "s_end",
        "command": "virtual_release",
        "hitline": 1,
        "execution": "r"
    },
    {
        "id": 55.5,
        "timestamp": 24.212999999999997,
        "hit_pos": -1,
        "hold_pos": 5,
        "note_width": [],
        "description": "",
        "command": "virtual_resume",
        "hitline": 2,
        "execution": "h"
    },
    {
        "id": 56,
        "timestamp": 24.82,
        "hit_pos": 7,
        "hold_pos": 3,
        "note_width": [
            6,
            7,
            8
        ],
        "description": "tap",
        "command": "tap",
        "hitline": 0,
        "execution": "t"
    },
    {
        "id": 57,
        "timestamp": 25.036,
        "hit_pos": 1,
        "hold_pos": 0,
        "note_width": [
            0,
            1,
            2
        ],
        "description": "tap",
        "command": "tap",
        "hitline": 0,
        "execution": "t"
    },
    {
        "id": 58,
        "timestamp": 25.252,
        "hit_pos": 9,
        "hold_pos": 5,
        "note_width": [
            9,
            10,
            11
        ],
        "description": "tap",
        "command": "tap",
        "hitline": 0,
        "execution": "t"
    },
    {
        "id": 59,
        "timestamp": 25.468,
        "hit_pos": 4,
        "hold_pos": 1,
        "note_width": [
            3,
            4,
            5
        ],
        "description": "tap",
        "command": "tap",
        "hitline": 0,
        "execution": "t"
    },
    {
        "id": 60,
        "timestamp": 25.683,
        "hit_pos": 7,
        "hold_pos": 3,
        "note_width": [
            6,
            7,
            8
        ],
        "description": "tap",
        "command": "tap",
        "hitline": 0,
        "execution": "t"
    },
    {
        "id": 61,
        "timestamp": 25.899,
        "hit_pos": 4,
        "hold_pos": 2,
        "note_width": [
            3,
            4,
            5
        ],
        "description": "s_start",
        "command": "tap",
        "hitline": 0,
        "execution": "t"
    },
    {
        "id": 62,
        "timestamp": 26.331,
        "hit_pos": 1,
        "hold_pos": 0,
        "note_width": [
            0,
            1,
            2
        ],
        "description": "s_end",
        "command": "virtual_release",
        "hitline": 1,
        "execution": "r"
    },
    {
        "id": 62.5,
        "timestamp": 26.371,
        "hit_pos": -1,
        "hold_pos": 0,
        "note_width": [],
        "description": "",
        "command": "virtual_resume",
        "hitline": 2,
        "execution": "h"
    },
    {
        "id": 63,
        "timestamp": 26.547,
        "hit_pos": 7,
        "hold_pos": 3,
        "note_width": [
            6,
            7,
            8
        ],
        "description": "s_start",
        "command": "tap",
        "hitline": 0,
        "execution": "t"
    },
    {
        "id": 64,
        "timestamp": 26.978,
        "hit_pos": 9,
        "hold_pos": 4,
        "note_width": [
            9,
            10,
            11
        ],
        "description": "s_end",
        "command": "virtual_release",
        "hitline": 2,
        "execution": "r"
    },
    {
        "id": 64.5,
        "timestamp": 27.018,
        "hit_pos": -1,
        "hold_pos": 4,
        "note_width": [],
        "description": "",
        "command": "virtual_resume",
        "hitline": 1,
        "execution": "h"
    },
    {
        "id": 65,
        "timestamp": 27.194,
        "hit_pos": 4,
        "hold_pos": 2,
        "note_width": [
            3,
            4,
            5
        ],
        "description": "tap",
        "command": "tap",
        "hitline": 0,
        "execution": "t"
    },
    {
        "id": 66,
        "timestamp": 27.41,
        "hit_pos": 9,
        "hold_pos": 5,
        "note_width": [
            9,
            10,
            11
        ],
        "description": "tap",
        "command": "tap",
        "hitline": 0,
        "execution": "t"
    },
    {
        "id": 67,
        "timestamp": 27.626,
        "hit_pos": 1,
        "hold_pos": 0,
        "note_width": [
            0,
            1,
            2
        ],
        "description": "tap",
        "command": "tap",
        "hitline": 0,
        "execution": "t"
    },
    {
        "id": 68,
        "timestamp": 27.842,
        "hit_pos": 7,
        "hold_pos": 3,
        "note_width": [
            6,
            7,
            8
        ],
        "description": "tap",
        "command": "tap",
        "hitline": 0,
        "execution": "t"
    },
    {
        "id": 69,
        "timestamp": 28.705,
        "hit_pos": 4,
        "hold_pos": 2,
        "note_width": [
            3,
            4,
            5
        ],
        "description": "tap",
        "command": "tap",
        "hitline": 0,
        "execution": "t"
    },
    {
        "id": 70,
        "timestamp": 28.921,
        "hit_pos": 9,
        "hold_pos": 5,
        "note_width": [
            9,
            10,
            11
        ],
        "description": "tap",
        "command": "tap",
        "hitline": 0,
        "execution": "t"
    },
    {
        "id": 71,
        "timestamp": 29.137,
        "hit_pos": 1,
        "hold_pos": 0,
        "note_width": [
            0,
            1,
            2
        ],
        "description": "tap",
        "command": "tap",
        "hitline": 0,
        "execution": "t"
    },
    {
        "id": 72,
        "timestamp": 29.353,
        "hit_pos": 7,
        "hold_pos": 3,
        "note_width": [
            6,
            7,
            8
        ],
        "description": "s_start",
        "command": "tap",
        "hitline": 0,
        "execution": "t"
    },
    {
        "id": 73,
        "timestamp": 29.784,
        "hit_pos": 9,
        "hold_pos": 4,
        "note_width": [
            9,
            10,
            11
        ],
        "description": "s_end",
        "command": "virtual_release",
        "hitline": 1,
        "execution": "r"
    },
    {
        "id": 73.5,
        "timestamp": 29.823999999999998,
        "hit_pos": -1,
        "hold_pos": 4,
        "note_width": [],
        "description": "",
        "command": "virtual_resume",
        "hitline": 2,
        "execution": "h"
    },
    {
        "id": 74,
        "timestamp": 30.0,
        "hit_pos": 4,
        "hold_pos": 2,
        "note_width": [
            3,
            4,
            5
        ],
        "description": "s_start",
        "command": "tap",
        "hitline": 0,
        "execution": "t"
    },
    {
        "id": 75,
        "timestamp": 30.432,
        "hit_pos": 1,
        "hold_pos": 0,
        "note_width": [
            0,
            1,
            2
        ],
        "description": "s_end",
        "command": "virtual_release",
        "hitline": 2,
        "execution": "r"
    },
    {
        "id": 75.5,
        "timestamp": 30.471999999999998,
        "hit_pos": -1,
        "hold_pos": 0,
        "note_width": [],
        "description": "",
        "command": "virtual_resume",
        "hitline": 1,
        "execution": "h"
    },
    {
        "id": 76,
        "timestamp": 30.863,
        "hit_pos": 9,
        "hold_pos": 5,
        "note_width": [
            9,
            10,
            11
        ],
        "description": "s_start",
        "command": "tap",
        "hitline": 0,
        "execution": "t"
    },
    {
        "id": 77,
        "timestamp": 31.295,
        "hit_pos": 7,
        "hold_pos": 3,
        "note_width": [
            6,
            7,
            8
        ],
        "description": "s_end",
        "command": "virtual_release",
        "hitline": 2,
        "execution": "r"
    },
    {
        "id": 77.5,
        "timestamp": 31.335,
        "hit_pos": -1,
        "hold_pos": 3,
        "note_width": [],
        "description": "",
        "command": "virtual_resume",
        "hitline": 1,
        "execution": "h"
    },
    {
        "id": 78,
        "timestamp": 31.511,
        "hit_pos": 1,
        "hold_pos": 0,
        "note_width": [
            0,
            1,
            2
        ],
        "description": "tap",
        "command": "tap",
        "hitline": 0,
        "execution": "t"
    },
    {
        "id": 79,
        "timestamp": 31.727,
        "hit_pos": 7,
        "hold_pos": 3,
        "note_width": [
            6,
            7,
            8
        ],
        "description": "tap",
        "command": "tap",
        "hitline": 0,
        "execution": "t"
    },
    {
        "id": 80,
        "timestamp": 31.942,
        "hit_pos": 4,
        "hold_pos": 2,
        "note_width": [
            3,
            4,
            5
        ],
        "description": "tap",
        "command": "tap",
        "hitline": 0,
        "execution": "t"
    },
    {
        "id": 81,
        "timestamp": 32.158,
        "hit_pos": 9,
        "hold_pos": 5,
        "note_width": [
            9,
            10,
            11
        ],
        "description": "tap",
        "command": "tap",
        "hitline": 0,
        "execution": "t"
    },
    {
        "id": 82,
        "timestamp": 32.374,
        "hit_pos": 1,
        "hold_pos": 0,
        "note_width": [
            0,
            1,
            2
        ],
        "description": "tap",
        "command": "tap",
        "hitline": 0,
        "execution": "t"
    },
    {
        "id": 83,
        "timestamp": 32.59,
        "hit_pos": 7,
        "hold_pos": 3,
        "note_width": [
            6,
            7,
            8
        ],
        "description": "tap",
        "command": "tap",
        "hitline": 0,
        "execution": "t"
    },
    {
        "id": 84,
        "timestamp": 32.806,
        "hit_pos": 4,
        "hold_pos": 2,
        "note_width": [
            3,
            4,
            5
        ],
        "description": "s_start",
        "command": "tap",
        "hitline": 0,
        "execution": "t"
    },
    {
        "id": 85,
        "timestamp": 33.237,
        "hit_pos": 1,
        "hold_pos": 0,
        "note_width": [
            0,
            1,
            2
        ],
        "description": "s_end",
        "command": "virtual_release",
        "hitline": 1,
        "execution": "r"
    },
    {
        "id": 85.5,
        "timestamp": 33.277,
        "hit_pos": -1,
        "hold_pos": 0,
        "note_width": [],
        "description": "",
        "command": "virtual_resume",
        "hitline": 2,
        "execution": "h"
    },
    {
        "id": 86,
        "timestamp": 33.453,
        "hit_pos": 7,
        "hold_pos": 3,
        "note_width": [
            6,
            7,
            8
        ],
        "description": "s_start",
        "command": "tap",
        "hitline": 0,
        "execution": "t"
    },
    {
        "id": 87,
        "timestamp": 34.147,
        "hit_pos": 9,
        "hold_pos": 4,
        "note_width": [
            9,
            10,
            11
        ],
        "description": "s_endfl_up",
        "command": "endflick",
        "hitline": 0,
        "execution": "f"
    },
    {
        "id": 88,
        "timestamp": 34.532,
        "hit_pos": 1,
        "hold_pos": 0,
        "note_width": [
            0,
            1,
            2
        ],
        "description": "tap",
        "command": "tap",
        "hitline": 0,
        "execution": "t"
    },
    {
        "id": 89,
        "timestamp": 34.532,
        "hit_pos": 9,
        "hold_pos": 5,
        "note_width": [
            9,
            10,
            11
        ],
        "description": "tap",
        "command": "tap",
        "hitline": 0,
        "execution": "t"
    },
    {
        "id": 90,
        "timestamp": 34.964,
        "hit_pos": 1,
        "hold_pos": 0,
        "note_width": [
            0,
            1,
            2
        ],
        "description": "tap",
        "command": "tap",
        "hitline": 0,
        "execution": "t"
    },
    {
        "id": 91,
        "timestamp": 35.18,
        "hit_pos": 7,
        "hold_pos": 3,
        "note_width": [
            6,
            7,
            8
        ],
        "description": "s_start",
        "command": "tap",
        "hitline": 0,
        "execution": "t"
    },
    {
        "id": 92,
        "timestamp": 35.612,
        "hit_pos": 9,
        "hold_pos": 5,
        "note_width": [
            9,
            10,
            11
        ],
        "description": "s_end",
        "command": "virtual_release",
        "hitline": 2,
        "execution": "r"
    },
    {
        "id": 92.5,
        "timestamp": 35.652,
        "hit_pos": -1,
        "hold_pos": 5,
        "note_width": [],
        "description": "",
        "command": "virtual_resume",
        "hitline": 1,
        "execution": "h"
    },
    {
        "id": 93,
        "timestamp": 36.043,
        "hit_pos": 4,
        "hold_pos": 1,
        "note_width": [
            3,
            4,
            5
        ],
        "description": "s_start",
        "command": "tap",
        "hitline": 0,
        "execution": "t"
    },
    {
        "id": 95,
        "timestamp": 36.906,
        "hit_pos": 4,
        "hold_pos": 1,
        "note_width": [
            3,
            4,
            5
        ],
        "description": "s_end",
        "command": "virtual_release",
        "hitline": 1,
        "execution": "r"
    },
    {
        "id": 95.5,
        "timestamp": 36.946,
        "hit_pos": -1,
        "hold_pos": 1,
        "note_width": [],
        "description": "",
        "command": "virtual_resume",
        "hitline": 2,
        "execution": "h"
    },
    {
        "id": 96,
        "timestamp": 37.338,
        "hit_pos": 7,
        "hold_pos": 3,
        "note_width": [
            6,
            7,
            8
        ],
        "description": "tap",
        "command": "tap",
        "hitline": 0,
        "execution": "t"
    },
    {
        "id": 97,
        "timestamp": 37.554,
        "hit_pos": 4,
        "hold_pos": 1,
        "note_width": [
            3,
            4,
            5
        ],
        "description": "tap",
        "command": "tap",
        "hitline": 0,
        "execution": "t"
    },
    {
        "id": 98,
        "timestamp": 37.77,
        "hit_pos": 7,
        "hold_pos": 3,
        "note_width": [
            6,
            7,
            8
        ],
        "description": "s_start",
        "command": "tap",
        "hitline": 0,
        "execution": "t"
    },
    {
        "id": 99,
        "timestamp": 38.849,
        "hit_pos": 9,
        "hold_pos": 5,
        "note_width": [
            9,
            10,
            11
        ],
        "description": "s_end",
        "command": "virtual_release",
        "hitline": 1,
        "execution": "r"
    },
    {
        "id": 99.5,
        "timestamp": 38.888999999999996,
        "hit_pos": -1,
        "hold_pos": 5,
        "note_width": [],
        "description": "",
        "command": "virtual_resume",
        "hitline": 2,
        "execution": "h"
    },
    {
        "id": 100,
        "timestamp": 39.065,
        "hit_pos": 4,
        "hold_pos": 1,
        "note_width": [
            3,
            4,
            5
        ],
        "description": "tap",
        "command": "tap",
        "hitline": 0,
        "execution": "t"
    },
    {
        "id": 101,
        "timestamp": 39.281,
        "hit_pos": 7,
        "hold_pos": 3,
        "note_width": [
            6,
            7,
            8
        ],
        "description": "tap",
        "command": "tap",
        "hitline": 0,
        "execution": "t"
    },
    {
        "id": 102,
        "timestamp": 39.496,
        "hit_pos": 4,
        "hold_pos": 1,
        "note_width": [
            3,
            4,
            5
        ],
        "description": "tap",
        "command": "tap",
        "hitline": 0,
        "execution": "t"
    },
    {
        "id": 103,
        "timestamp": 39.712,
        "hit_pos": 9,
        "hold_pos": 5,
        "note_width": [
            9,
            10,
            11
        ],
        "description": "tap",
        "command": "tap",
        "hitline": 0,
        "execution": "t"
    },
    {
        "id": 104,
        "timestamp": 39.928,
        "hit_pos": 4,
        "hold_pos": 2,
        "note_width": [
            3,
            4,
            5
        ],
        "description": "tap",
        "command": "tap",
        "hitline": 0,
        "execution": "t"
    },
    {
        "id": 105,
        "timestamp": 40.144,
        "hit_pos": 7,
        "hold_pos": 3,
        "note_width": [
            6,
            7,
            8
        ],
        "description": "tap",
        "command": "tap",
        "hitline": 0,
        "execution": "t"
    },
    {
        "id": 106,
        "timestamp": 40.36,
        "hit_pos": 1,
        "hold_pos": 0,
        "note_width": [
            0,
            1,
            2
        ],
        "description": "tap",
        "command": "tap",
        "hitline": 0,
        "execution": "t"
    },
    {
        "id": 107,
        "timestamp": 40.576,
        "hit_pos": 9,
        "hold_pos": 5,
        "note_width": [
            9,
            10,
            11
        ],
        "description": "tap",
        "command": "tap",
        "hitline": 0,
        "execution": "t"
    },
    {
        "id": 108,
        "timestamp": 40.791,
        "hit_pos": 4,
        "hold_pos": 1,
        "note_width": [
            3,
            4,
            5
        ],
        "description": "tap",
        "command": "tap",
        "hitline": 0,
        "execution": "t"
    },
    {
        "id": 109,
        "timestamp": 41.007,
        "hit_pos": 7,
        "hold_pos": 3,
        "note_width": [
            6,
            7,
            8
        ],
        "description": "tap",
        "command": "tap",
        "hitline": 0,
        "execution": "t"
    },
    {
        "id": 110,
        "timestamp": 41.223,
        "hit_pos": 4,
        "hold_pos": 2,
        "note_width": [
            3,
            4,
            5
        ],
        "description": "s_start",
        "command": "tap",
        "hitline": 0,
        "execution": "t"
    },
    {
        "id": 111,
        "timestamp": 41.871,
        "hit_pos": 1,
        "hold_pos": 0,
        "note_width": [
            0,
            1,
            2
        ],
        "description": "s_end",
        "command": "virtual_release",
        "hitline": 2,
        "execution": "r"
    },
    {
        "id": 111.5,
        "timestamp": 41.911,
        "hit_pos": -1,
        "hold_pos": 0,
        "note_width": [],
        "description": "",
        "command": "virtual_resume",
        "hitline": 1,
        "execution": "h"
    },
    {
        "id": 112,
        "timestamp": 42.086,
        "hit_pos": 7,
        "hold_pos": 3,
        "note_width": [
            6,
            7,
            8
        ],
        "description": "tap",
        "command": "tap",
        "hitline": 0,
        "execution": "t"
    },
    {
        "id": 113,
        "timestamp": 42.302,
        "hit_pos": 4,
        "hold_pos": 2,
        "note_width": [
            3,
            4,
            5
        ],
        "description": "tap",
        "command": "tap",
        "hitline": 0,
        "execution": "t"
    },
    {
        "id": 114,
        "timestamp": 42.518,
        "hit_pos": 9,
        "hold_pos": 5,
        "note_width": [
            9,
            10,
            11
        ],
        "description": "tap",
        "command": "tap",
        "hitline": 0,
        "execution": "t"
    },
    {
        "id": 115,
        "timestamp": 42.734,
        "hit_pos": 1,
        "hold_pos": 0,
        "note_width": [
            0,
            1,
            2
        ],
        "description": "tap",
        "command": "tap",
        "hitline": 0,
        "execution": "t"
    },
    {
        "id": 116,
        "timestamp": 42.95,
        "hit_pos": 7,
        "hold_pos": 3,
        "note_width": [
            6,
            7,
            8
        ],
        "description": "s_start",
        "command": "tap",
        "hitline": 0,
        "execution": "t"
    },
    {
        "id": 117,
        "timestamp": 43.813,
        "hit_pos": 9,
        "hold_pos": 5,
        "note_width": [
            9,
            10,
            11
        ],
        "description": "s_end",
        "command": "virtual_release",
        "hitline": 2,
        "execution": "r"
    },
    {
        "id": 117.5,
        "timestamp": 43.853,
        "hit_pos": -1,
        "hold_pos": 5,
        "note_width": [],
        "description": "",
        "command": "virtual_resume",
        "hitline": 1,
        "execution": "h"
    },
    {
        "id": 118,
        "timestamp": 44.245,
        "hit_pos": 4,
        "hold_pos": 1,
        "note_width": [
            3,
            4,
            5
        ],
        "description": "tap",
        "command": "tap",
        "hitline": 0,
        "execution": "t"
    },
    {
        "id": 119,
        "timestamp": 44.46,
        "hit_pos": 7,
        "hold_pos": 3,
        "note_width": [
            6,
            7,
            8
        ],
        "description": "tap",
        "command": "tap",
        "hitline": 0,
        "execution": "t"
    },
    {
        "id": 120,
        "timestamp": 44.676,
        "hit_pos": 4,
        "hold_pos": 2,
        "note_width": [
            3,
            4,
            5
        ],
        "description": "tap",
        "command": "tap",
        "hitline": 0,
        "execution": "t"
    },
    {
        "id": 121,
        "timestamp": 44.892,
        "hit_pos": 9,
        "hold_pos": 4,
        "note_width": [
            9,
            10,
            11
        ],
        "description": "tap",
        "command": "tap",
        "hitline": 0,
        "execution": "t"
    },
    {
        "id": 122,
        "timestamp": 45.108,
        "hit_pos": 1,
        "hold_pos": 0,
        "note_width": [
            0,
            1,
            2
        ],
        "description": "tap",
        "command": "tap",
        "hitline": 0,
        "execution": "t"
    },
    {
        "id": 123,
        "timestamp": 45.324,
        "hit_pos": 9,
        "hold_pos": 5,
        "note_width": [
            9,
            10,
            11
        ],
        "description": "tap",
        "command": "tap",
        "hitline": 0,
        "execution": "t"
    },
    {
        "id": 124,
        "timestamp": 45.54,
        "hit_pos": 1,
        "hold_pos": 0,
        "note_width": [
            0,
            1,
            2
        ],
        "description": "tap",
        "command": "tap",
        "hitline": 0,
        "execution": "t"
    },
    {
        "id": 125,
        "timestamp": 45.755,
        "hit_pos": 7,
        "hold_pos": 3,
        "note_width": [
            6,
            7,
            8
        ],
        "description": "tap",
        "command": "tap",
        "hitline": 0,
        "execution": "t"
    },
    {
        "id": 126,
        "timestamp": 45.971,
        "hit_pos": 4,
        "hold_pos": 2,
        "note_width": [
            3,
            4,
            5
        ],
        "description": "tap",
        "command": "tap",
        "hitline": 0,
        "execution": "t"
    },
    {
        "id": 127,
        "timestamp": 46.187,
        "hit_pos": 9,
        "hold_pos": 5,
        "note_width": [
            9,
            10,
            11
        ],
        "description": "tap",
        "command": "tap",
        "hitline": 0,
        "execution": "t"
    },
    {
        "id": 128,
        "timestamp": 46.403,
        "hit_pos": 1,
        "hold_pos": 0,
        "note_width": [
            0,
            1,
            2
        ],
        "description": "tap",
        "command": "tap",
        "hitline": 0,
        "execution": "t"
    },
    {
        "id": 129,
        "timestamp": 46.619,
        "hit_pos": 7,
        "hold_pos": 3,
        "note_width": [
            6,
            7,
            8
        ],
        "description": "s_start",
        "command": "tap",
        "hitline": 0,
        "execution": "t"
    },
    {
        "id": 135,
        "timestamp": 47.914,
        "hit_pos": 9,
        "hold_pos": 4,
        "note_width": [
            9,
            10,
            11
        ],
        "description": "s_end",
        "command": "virtual_release",
        "hitline": 2,
        "execution": "r"
    },
    {
        "id": 135.5,
        "timestamp": 47.954,
        "hit_pos": -1,
        "hold_pos": 4,
        "note_width": [],
        "description": "",
        "command": "virtual_resume",
        "hitline": 1,
        "execution": "h"
    },
    {
        "id": 136,
        "timestamp": 48.345,
        "hit_pos": 4,
        "hold_pos": 2,
        "note_width": [
            3,
            4,
            5
        ],
        "description": "s_start",
        "command": "tap",
        "hitline": 0,
        "execution": "t"
    },
    {
        "id": 137,
        "timestamp": 48.345,
        "hit_pos": 9,
        "hold_pos": 5,
        "note_width": [
            9,
            10,
            11
        ],
        "description": "tap",
        "command": "tap",
        "hitline": 0,
        "execution": "t"
    },
    {
        "id": 138,
        "timestamp": 49.209,
        "hit_pos": 7,
        "hold_pos": 3,
        "note_width": [
            6,
            7,
            8
        ],
        "description": "tap",
        "command": "tap",
        "hitline": 0,
        "execution": "t"
    },
    {
        "id": 139,
        "timestamp": 50.072,
        "hit_pos": 9,
        "hold_pos": 5,
        "note_width": [
            9,
            10,
            11
        ],
        "description": "tap",
        "command": "tap",
        "hitline": 0,
        "execution": "t"
    },
    {
        "id": 140,
        "timestamp": 50.935,
        "hit_pos": 1,
        "hold_pos": 0,
        "note_width": [
            0,
            1,
            2
        ],
        "description": "s_end",
        "command": "virtual_release",
        "hitline": 1,
        "execution": "r"
    },
    {
        "id": 141,
        "timestamp": 50.935,
        "hit_pos": 7,
        "hold_pos": 3,
        "note_width": [
            6,
            7,
            8
        ],
        "description": "tap",
        "command": "tap",
        "hitline": 0,
        "execution": "t"
    },
    {
        "id": 140.5,
        "timestamp": 50.975,
        "hit_pos": -1,
        "hold_pos": 0,
        "note_width": [],
        "description": "",
        "command": "virtual_resume",
        "hitline": 2,
        "execution": "h"
    },
    {
        "id": 142,
        "timestamp": 51.799,
        "hit_pos": 1,
        "hold_pos": 0,
        "note_width": [
            0,
            1,
            2
        ],
        "description": "tap",
        "command": "tap",
        "hitline": 0,
        "execution": "t"
    },
    {
        "id": 143,
        "timestamp": 51.799,
        "hit_pos": 7,
        "hold_pos": 3,
        "note_width": [
            6,
            7,
            8
        ],
        "description": "s_start",
        "command": "tap",
        "hitline": 0,
        "execution": "t"
    },
    {
        "id": 144,
        "timestamp": 52.662,
        "hit_pos": 4,
        "hold_pos": 2,
        "note_width": [
            3,
            4,
            5
        ],
        "description": "tap",
        "command": "tap",
        "hitline": 0,
        "execution": "t"
    },
    {
        "id": 145,
        "timestamp": 53.525,
        "hit_pos": 1,
        "hold_pos": 0,
        "note_width": [
            0,
            1,
            2
        ],
        "description": "tap",
        "command": "tap",
        "hitline": 0,
        "execution": "t"
    },
    {
        "id": 146,
        "timestamp": 54.388,
        "hit_pos": 4,
        "hold_pos": 1,
        "note_width": [
            3,
            4,
            5
        ],
        "description": "tap",
        "command": "tap",
        "hitline": 0,
        "execution": "t"
    },
    {
        "id": 147,
        "timestamp": 54.388,
        "hit_pos": 9,
        "hold_pos": 5,
        "note_width": [
            9,
            10,
            11
        ],
        "description": "s_end",
        "command": "virtual_release",
        "hitline": 1,
        "execution": "r"
    },
    {
        "id": 147.5,
        "timestamp": 54.428,
        "hit_pos": -1,
        "hold_pos": 5,
        "note_width": [],
        "description": "",
        "command": "virtual_resume",
        "hitline": 2,
        "execution": "h"
    },
    {
        "id": 148,
        "timestamp": 54.604,
        "hit_pos": 7,
        "hold_pos": 3,
        "note_width": [
            6,
            7,
            8
        ],
        "description": "tap",
        "command": "tap",
        "hitline": 0,
        "execution": "t"
    },
    {
        "id": 149,
        "timestamp": 54.82,
        "hit_pos": 4,
        "hold_pos": 2,
        "note_width": [
            3,
            4,
            5
        ],
        "description": "tap",
        "command": "tap",
        "hitline": 0,
        "execution": "t"
    },
    {
        "id": 150,
        "timestamp": 55.036,
        "hit_pos": 1,
        "hold_pos": 0,
        "note_width": [
            0,
            1,
            2
        ],
        "description": "tap",
        "command": "tap",
        "hitline": 0,
        "execution": "t"
    },
    {
        "id": 151,
        "timestamp": 55.252,
        "hit_pos": 7,
        "hold_pos": 3,
        "note_width": [
            6,
            7,
            8
        ],
        "description": "s_start",
        "command": "tap",
        "hitline": 0,
        "execution": "t"
    },
    {
        "id": 152,
        "timestamp": 55.729,
        "hit_pos": 7,
        "hold_pos": 3,
        "note_width": [
            6,
            7,
            8
        ],
        "description": "s_endfl_up",
        "command": "endflick",
        "hitline": 0,
        "execution": "f"
    },
    {
        "id": 153,
        "timestamp": 56.115,
        "hit_pos": 4,
        "hold_pos": 1,
        "note_width": [
            3,
            4,
            5
        ],
        "description": "tap",
        "command": "tap",
        "hitline": 0,
        "execution": "t"
    },
    {
        "id": 154,
        "timestamp": 56.331,
        "hit_pos": 7,
        "hold_pos": 3,
        "note_width": [
            6,
            7,
            8
        ],
        "description": "tap",
        "command": "tap",
        "hitline": 0,
        "execution": "t"
    },
    {
        "id": 155,
        "timestamp": 56.547,
        "hit_pos": 9,
        "hold_pos": 5,
        "note_width": [
            9,
            10,
            11
        ],
        "description": "tap",
        "command": "tap",
        "hitline": 0,
        "execution": "t"
    },
    {
        "id": 156,
        "timestamp": 56.763,
        "hit_pos": 4,
        "hold_pos": 1,
        "note_width": [
            3,
            4,
            5
        ],
        "description": "s_start",
        "command": "tap",
        "hitline": 0,
        "execution": "t"
    },
    {
        "id": 157,
        "timestamp": 57.24,
        "hit_pos": 4,
        "hold_pos": 1,
        "note_width": [
            3,
            4,
            5
        ],
        "description": "s_endfl_up",
        "command": "endflick",
        "hitline": 0,
        "execution": "f"
    },
    {
        "id": 158,
        "timestamp": 57.626,
        "hit_pos": 7,
        "hold_pos": 3,
        "note_width": [
            6,
            7,
            8
        ],
        "description": "tap",
        "command": "tap",
        "hitline": 0,
        "execution": "t"
    },
    {
        "id": 159,
        "timestamp": 57.842,
        "hit_pos": 4,
        "hold_pos": 1,
        "note_width": [
            3,
            4,
            5
        ],
        "description": "tap",
        "command": "tap",
        "hitline": 0,
        "execution": "t"
    },
    {
        "id": 160,
        "timestamp": 58.058,
        "hit_pos": 7,
        "hold_pos": 3,
        "note_width": [
            6,
            7,
            8
        ],
        "description": "tap",
        "command": "tap",
        "hitline": 0,
        "execution": "t"
    },
    {
        "id": 161,
        "timestamp": 58.273,
        "hit_pos": 4,
        "hold_pos": 1,
        "note_width": [
            3,
            4,
            5
        ],
        "description": "tap",
        "command": "tap",
        "hitline": 0,
        "execution": "t"
    },
    {
        "id": 162,
        "timestamp": 58.489,
        "hit_pos": 7,
        "hold_pos": 3,
        "note_width": [
            6,
            7,
            8
        ],
        "description": "tap",
        "command": "tap",
        "hitline": 0,
        "execution": "t"
    },
    {
        "id": 163,
        "timestamp": 58.711,
        "hit_pos": 3,
        "hold_pos": 2,
        "note_width": [
            0,
            1,
            2,
            3,
            4,
            5
        ],
        "description": "c_c_tapfl_up",
        "command": "flick",
        "hitline": 0,
        "execution": "f"
    },
    {
        "id": 164,
        "timestamp": 60.438,
        "hit_pos": 2,
        "hold_pos": 0,
        "note_width": [
            0,
            1,
            2,
            3
        ],
        "description": "c_c_tapfl_up",
        "command": "flick",
        "hitline": 0,
        "execution": "f"
    },
    {
        "id": 165,
        "timestamp": 60.438,
        "hit_pos": 9,
        "hold_pos": 5,
        "note_width": [
            8,
            9,
            10,
            11
        ],
        "description": "c_c_tapfl_up",
        "command": "flick",
        "hitline": 0,
        "execution": "f"
    },
    {
        "id": 166,
        "timestamp": 60.863,
        "hit_pos": 7,
        "hold_pos": 3,
        "note_width": [
            6,
            7,
            8
        ],
        "description": "tap",
        "command": "tap",
        "hitline": 0,
        "execution": "t"
    },
    {
        "id": 167,
        "timestamp": 61.079,
        "hit_pos": 4,
        "hold_pos": 1,
        "note_width": [
            3,
            4,
            5
        ],
        "description": "c_tap",
        "command": "tap",
        "hitline": 0,
        "execution": "t"
    },
    {
        "id": 168,
        "timestamp": 61.511,
        "hit_pos": 7,
        "hold_pos": 3,
        "note_width": [
            6,
            7,
            8
        ],
        "description": "tap",
        "command": "tap",
        "hitline": 0,
        "execution": "t"
    },
    {
        "id": 169,
        "timestamp": 61.727,
        "hit_pos": 4,
        "hold_pos": 1,
        "note_width": [
            3,
            4,
            5
        ],
        "description": "tap",
        "command": "tap",
        "hitline": 0,
        "execution": "t"
    },
    {
        "id": 170,
        "timestamp": 61.942,
        "hit_pos": 7,
        "hold_pos": 4,
        "note_width": [
            6,
            7,
            8
        ],
        "description": "tap",
        "command": "tap",
        "hitline": 0,
        "execution": "t"
    },
    {
        "id": 171,
        "timestamp": 62.158,
        "hit_pos": 3,
        "hold_pos": 2,
        "note_width": [
            2,
            3,
            4,
            5
        ],
        "description": "s_start",
        "command": "tap",
        "hitline": 0,
        "execution": "t"
    },
    {
        "id": 179,
        "timestamp": 63.885,
        "hit_pos": 2,
        "hold_pos": 0,
        "note_width": [
            0,
            1,
            2,
            3
        ],
        "description": "s_end",
        "command": "virtual_release",
        "hitline": 2,
        "execution": "r"
    },
    {
        "id": 179.5,
        "timestamp": 63.925,
        "hit_pos": -1,
        "hold_pos": 0,
        "note_width": [],
        "description": "",
        "command": "virtual_resume",
        "hitline": 1,
        "execution": "h"
    },
    {
        "id": 180,
        "timestamp": 64.317,
        "hit_pos": 5,
        "hold_pos": 2,
        "note_width": [
            4,
            5,
            6,
            7
        ],
        "description": "c_tap",
        "command": "tap",
        "hitline": 0,
        "execution": "t"
    },
    {
        "id": 181,
        "timestamp": 64.754,
        "hit_pos": 2,
        "hold_pos": 0,
        "note_width": [
            0,
            1,
            2,
            3
        ],
        "description": "c_c_tapfl_up",
        "command": "flick",
        "hitline": 0,
        "execution": "f"
    },
    {
        "id": 182,
        "timestamp": 64.754,
        "hit_pos": 9,
        "hold_pos": 5,
        "note_width": [
            8,
            9,
            10,
            11
        ],
        "description": "c_c_tapfl_up",
        "command": "flick",
        "hitline": 0,
        "execution": "f"
    },
    {
        "id": 183,
        "timestamp": 65.18,
        "hit_pos": 7,
        "hold_pos": 3,
        "note_width": [
            6,
            7,
            8
        ],
        "description": "s_start",
        "command": "tap",
        "hitline": 0,
        "execution": "t"
    },
    {
        "id": 187,
        "timestamp": 65.612,
        "hit_pos": 9,
        "hold_pos": 4,
        "note_width": [
            9,
            10,
            11
        ],
        "description": "s_end",
        "command": "virtual_release",
        "hitline": 1,
        "execution": "r"
    },
    {
        "id": 187.5,
        "timestamp": 65.652,
        "hit_pos": -1,
        "hold_pos": 4,
        "note_width": [],
        "description": "",
        "command": "virtual_resume",
        "hitline": 2,
        "execution": "h"
    },
    {
        "id": 188,
        "timestamp": 66.043,
        "hit_pos": 9,
        "hold_pos": 5,
        "note_width": [
            9,
            10,
            11
        ],
        "description": "tap",
        "command": "tap",
        "hitline": 0,
        "execution": "t"
    },
    {
        "id": 189,
        "timestamp": 66.259,
        "hit_pos": 4,
        "hold_pos": 2,
        "note_width": [
            3,
            4,
            5
        ],
        "description": "tap",
        "command": "tap",
        "hitline": 0,
        "execution": "t"
    },
    {
        "id": 190,
        "timestamp": 66.691,
        "hit_pos": 7,
        "hold_pos": 3,
        "note_width": [
            6,
            7,
            8
        ],
        "description": "tap",
        "command": "tap",
        "hitline": 0,
        "execution": "t"
    },
    {
        "id": 191,
        "timestamp": 66.906,
        "hit_pos": 1,
        "hold_pos": 0,
        "note_width": [
            0,
            1,
            2
        ],
        "description": "tap",
        "command": "tap",
        "hitline": 0,
        "execution": "t"
    },
    {
        "id": 192,
        "timestamp": 67.122,
        "hit_pos": 9,
        "hold_pos": 5,
        "note_width": [
            9,
            10,
            11
        ],
        "description": "s_start",
        "command": "tap",
        "hitline": 0,
        "execution": "t"
    },
    {
        "id": 193,
        "timestamp": 67.554,
        "hit_pos": 7,
        "hold_pos": 3,
        "note_width": [
            6,
            7,
            8
        ],
        "description": "s_end",
        "command": "virtual_release",
        "hitline": 1,
        "execution": "r"
    },
    {
        "id": 193.5,
        "timestamp": 67.59400000000001,
        "hit_pos": -1,
        "hold_pos": 3,
        "note_width": [],
        "description": "",
        "command": "virtual_resume",
        "hitline": 2,
        "execution": "h"
    },
    {
        "id": 194,
        "timestamp": 67.986,
        "hit_pos": 7,
        "hold_pos": 3,
        "note_width": [
            6,
            7,
            8
        ],
        "description": "tap",
        "command": "tap",
        "hitline": 0,
        "execution": "t"
    },
    {
        "id": 195,
        "timestamp": 68.201,
        "hit_pos": 4,
        "hold_pos": 2,
        "note_width": [
            3,
            4,
            5
        ],
        "description": "tap",
        "command": "tap",
        "hitline": 0,
        "execution": "t"
    },
    {
        "id": 196,
        "timestamp": 68.417,
        "hit_pos": 1,
        "hold_pos": 0,
        "note_width": [
            0,
            1,
            2
        ],
        "description": "tap",
        "command": "tap",
        "hitline": 0,
        "execution": "t"
    },
    {
        "id": 197,
        "timestamp": 68.849,
        "hit_pos": 7,
        "hold_pos": 3,
        "note_width": [
            6,
            7,
            8
        ],
        "description": "tap",
        "command": "tap",
        "hitline": 0,
        "execution": "t"
    },
    {
        "id": 198,
        "timestamp": 69.065,
        "hit_pos": 4,
        "hold_pos": 2,
        "note_width": [
            3,
            4,
            5
        ],
        "description": "s_start",
        "command": "tap",
        "hitline": 0,
        "execution": "t"
    },
    {
        "id": 199,
        "timestamp": 69.496,
        "hit_pos": 1,
        "hold_pos": 0,
        "note_width": [
            0,
            1,
            2
        ],
        "description": "s_end",
        "command": "virtual_release",
        "hitline": 1,
        "execution": "r"
    },
    {
        "id": 199.5,
        "timestamp": 69.536,
        "hit_pos": -1,
        "hold_pos": 0,
        "note_width": [],
        "description": "",
        "command": "virtual_resume",
        "hitline": 2,
        "execution": "h"
    },
    {
        "id": 200,
        "timestamp": 69.712,
        "hit_pos": 7,
        "hold_pos": 3,
        "note_width": [
            6,
            7,
            8
        ],
        "description": "tap",
        "command": "tap",
        "hitline": 0,
        "execution": "t"
    },
    {
        "id": 201,
        "timestamp": 70.144,
        "hit_pos": 4,
        "hold_pos": 1,
        "note_width": [
            3,
            4,
            5
        ],
        "description": "tap",
        "command": "tap",
        "hitline": 0,
        "execution": "t"
    },
    {
        "id": 202,
        "timestamp": 70.36,
        "hit_pos": 7,
        "hold_pos": 3,
        "note_width": [
            6,
            7,
            8
        ],
        "description": "tap",
        "command": "tap",
        "hitline": 0,
        "execution": "t"
    },
    {
        "id": 203,
        "timestamp": 70.576,
        "hit_pos": 9,
        "hold_pos": 4,
        "note_width": [
            9,
            10,
            11
        ],
        "description": "tap",
        "command": "tap",
        "hitline": 0,
        "execution": "t"
    },
    {
        "id": 204,
        "timestamp": 70.791,
        "hit_pos": 4,
        "hold_pos": 2,
        "note_width": [
            3,
            4,
            5
        ],
        "description": "s_start",
        "command": "tap",
        "hitline": 0,
        "execution": "t"
    },
    {
        "id": 205,
        "timestamp": 71.655,
        "hit_pos": 1,
        "hold_pos": 0,
        "note_width": [
            0,
            1,
            2
        ],
        "description": "s_end",
        "command": "virtual_release",
        "hitline": 2,
        "execution": "r"
    },
    {
        "id": 205.5,
        "timestamp": 71.69500000000001,
        "hit_pos": -1,
        "hold_pos": 0,
        "note_width": [],
        "description": "",
        "command": "virtual_resume",
        "hitline": 1,
        "execution": "h"
    },
    {
        "id": 206,
        "timestamp": 71.871,
        "hit_pos": 9,
        "hold_pos": 4,
        "note_width": [
            9,
            10,
            11
        ],
        "description": "tap",
        "command": "tap",
        "hitline": 0,
        "execution": "t"
    },
    {
        "id": 207,
        "timestamp": 72.086,
        "hit_pos": 9,
        "hold_pos": 5,
        "note_width": [
            9,
            10,
            11
        ],
        "description": "tap",
        "command": "tap",
        "hitline": 0,
        "execution": "t"
    },
    {
        "id": 208,
        "timestamp": 72.302,
        "hit_pos": 4,
        "hold_pos": 1,
        "note_width": [
            3,
            4,
            5
        ],
        "description": "tap",
        "command": "tap",
        "hitline": 0,
        "execution": "t"
    },
    {
        "id": 209,
        "timestamp": 72.518,
        "hit_pos": 7,
        "hold_pos": 3,
        "note_width": [
            6,
            7,
            8
        ],
        "description": "tap",
        "command": "tap",
        "hitline": 0,
        "execution": "t"
    },
    {
        "id": 210,
        "timestamp": 72.734,
        "hit_pos": 4,
        "hold_pos": 2,
        "note_width": [
            3,
            4,
            5
        ],
        "description": "tap",
        "command": "tap",
        "hitline": 0,
        "execution": "t"
    },
    {
        "id": 211,
        "timestamp": 72.95,
        "hit_pos": 9,
        "hold_pos": 5,
        "note_width": [
            9,
            10,
            11
        ],
        "description": "tap",
        "command": "tap",
        "hitline": 0,
        "execution": "t"
    },
    {
        "id": 212,
        "timestamp": 73.381,
        "hit_pos": 1,
        "hold_pos": 0,
        "note_width": [
            0,
            1,
            2
        ],
        "description": "tap",
        "command": "tap",
        "hitline": 0,
        "execution": "t"
    },
    {
        "id": 213,
        "timestamp": 73.597,
        "hit_pos": 7,
        "hold_pos": 3,
        "note_width": [
            6,
            7,
            8
        ],
        "description": "tap",
        "command": "tap",
        "hitline": 0,
        "execution": "t"
    },
    {
        "id": 214,
        "timestamp": 73.813,
        "hit_pos": 4,
        "hold_pos": 1,
        "note_width": [
            3,
            4,
            5
        ],
        "description": "tap",
        "command": "tap",
        "hitline": 0,
        "execution": "t"
    },
    {
        "id": 215,
        "timestamp": 74.029,
        "hit_pos": 7,
        "hold_pos": 3,
        "note_width": [
            6,
            7,
            8
        ],
        "description": "s_start",
        "command": "tap",
        "hitline": 0,
        "execution": "t"
    },
    {
        "id": 216,
        "timestamp": 74.506,
        "hit_pos": 9,
        "hold_pos": 5,
        "note_width": [
            9,
            10,
            11
        ],
        "description": "s_endfl_up",
        "command": "endflick",
        "hitline": 0,
        "execution": "f"
    },
    {
        "id": 217,
        "timestamp": 74.892,
        "hit_pos": 4,
        "hold_pos": 2,
        "note_width": [
            3,
            4,
            5
        ],
        "description": "tap",
        "command": "tap",
        "hitline": 0,
        "execution": "t"
    },
    {
        "id": 218,
        "timestamp": 75.108,
        "hit_pos": 7,
        "hold_pos": 3,
        "note_width": [
            6,
            7,
            8
        ],
        "description": "tap",
        "command": "tap",
        "hitline": 0,
        "execution": "t"
    },
    {
        "id": 219,
        "timestamp": 75.33,
        "hit_pos": 1,
        "hold_pos": 0,
        "note_width": [
            0,
            1,
            2
        ],
        "description": "tapfl_up",
        "command": "flick",
        "hitline": 0,
        "execution": "f"
    },
    {
        "id": 220,
        "timestamp": 75.755,
        "hit_pos": 7,
        "hold_pos": 3,
        "note_width": [
            6,
            7,
            8
        ],
        "description": "tap",
        "command": "tap",
        "hitline": 0,
        "execution": "t"
    },
    {
        "id": 221,
        "timestamp": 75.971,
        "hit_pos": 1,
        "hold_pos": 0,
        "note_width": [
            0,
            1,
            2
        ],
        "description": "c_tap",
        "command": "tap",
        "hitline": 0,
        "execution": "t"
    },
    {
        "id": 222,
        "timestamp": 76.187,
        "hit_pos": 9,
        "hold_pos": 5,
        "note_width": [
            9,
            10,
            11
        ],
        "description": "tap",
        "command": "tap",
        "hitline": 0,
        "execution": "t"
    },
    {
        "id": 223,
        "timestamp": 76.403,
        "hit_pos": 4,
        "hold_pos": 2,
        "note_width": [
            3,
            4,
            5
        ],
        "description": "c_tap",
        "command": "tap",
        "hitline": 0,
        "execution": "t"
    },
    {
        "id": 224,
        "timestamp": 76.619,
        "hit_pos": 7,
        "hold_pos": 3,
        "note_width": [
            6,
            7,
            8
        ],
        "description": "tap",
        "command": "tap",
        "hitline": 0,
        "execution": "t"
    },
    {
        "id": 225,
        "timestamp": 76.835,
        "hit_pos": 1,
        "hold_pos": 0,
        "note_width": [
            0,
            1,
            2
        ],
        "description": "c_tap",
        "command": "tap",
        "hitline": 0,
        "execution": "t"
    },
    {
        "id": 226,
        "timestamp": 77.266,
        "hit_pos": 9,
        "hold_pos": 5,
        "note_width": [
            9,
            10,
            11
        ],
        "description": "tap",
        "command": "tap",
        "hitline": 0,
        "execution": "t"
    },
    {
        "id": 227,
        "timestamp": 77.482,
        "hit_pos": 4,
        "hold_pos": 2,
        "note_width": [
            3,
            4,
            5
        ],
        "description": "s_start",
        "command": "tap",
        "hitline": 0,
        "execution": "t"
    },
    {
        "id": 228,
        "timestamp": 78.60700000000001,
        "hit_pos": 1,
        "hold_pos": 0,
        "note_width": [
            0,
            1,
            2
        ],
        "description": "s_endfl_up",
        "command": "endflick",
        "hitline": 0,
        "execution": "f"
    },
    {
        "id": 229,
        "timestamp": 79.209,
        "hit_pos": 7,
        "hold_pos": 3,
        "note_width": [
            6,
            7,
            8
        ],
        "description": "tap",
        "command": "tap",
        "hitline": 0,
        "execution": "t"
    },
    {
        "id": 230,
        "timestamp": 79.424,
        "hit_pos": 1,
        "hold_pos": 0,
        "note_width": [
            0,
            1,
            2
        ],
        "description": "s_start",
        "command": "tap",
        "hitline": 0,
        "execution": "t"
    },
    {
        "id": 231,
        "timestamp": 79.856,
        "hit_pos": 4,
        "hold_pos": 1,
        "note_width": [
            3,
            4,
            5
        ],
        "description": "s_end",
        "command": "virtual_release",
        "hitline": 2,
        "execution": "r"
    },
    {
        "id": 231.5,
        "timestamp": 79.896,
        "hit_pos": -1,
        "hold_pos": 1,
        "note_width": [],
        "description": "",
        "command": "virtual_resume",
        "hitline": 1,
        "execution": "h"
    },
    {
        "id": 232,
        "timestamp": 80.072,
        "hit_pos": 7,
        "hold_pos": 3,
        "note_width": [
            6,
            7,
            8
        ],
        "description": "tap",
        "command": "tap",
        "hitline": 0,
        "execution": "t"
    },
    {
        "id": 233,
        "timestamp": 80.504,
        "hit_pos": 4,
        "hold_pos": 2,
        "note_width": [
            3,
            4,
            5
        ],
        "description": "tap",
        "command": "tap",
        "hitline": 0,
        "execution": "t"
    },
    {
        "id": 234,
        "timestamp": 80.719,
        "hit_pos": 9,
        "hold_pos": 5,
        "note_width": [
            9,
            10,
            11
        ],
        "description": "tap",
        "command": "tap",
        "hitline": 0,
        "execution": "t"
    },
    {
        "id": 235,
        "timestamp": 80.935,
        "hit_pos": 1,
        "hold_pos": 0,
        "note_width": [
            0,
            1,
            2
        ],
        "description": "s_start",
        "command": "tap",
        "hitline": 0,
        "execution": "t"
    },
    {
        "id": 236,
        "timestamp": 81.367,
        "hit_pos": 4,
        "hold_pos": 1,
        "note_width": [
            3,
            4,
            5
        ],
        "description": "s_end",
        "command": "virtual_release",
        "hitline": 1,
        "execution": "r"
    },
    {
        "id": 236.5,
        "timestamp": 81.40700000000001,
        "hit_pos": -1,
        "hold_pos": 1,
        "note_width": [],
        "description": "",
        "command": "virtual_resume",
        "hitline": 2,
        "execution": "h"
    },
    {
        "id": 237,
        "timestamp": 81.799,
        "hit_pos": 4,
        "hold_pos": 1,
        "note_width": [
            3,
            4,
            5
        ],
        "description": "tap",
        "command": "tap",
        "hitline": 0,
        "execution": "t"
    },
    {
        "id": 238,
        "timestamp": 82.014,
        "hit_pos": 7,
        "hold_pos": 3,
        "note_width": [
            6,
            7,
            8
        ],
        "description": "tap",
        "command": "tap",
        "hitline": 0,
        "execution": "t"
    },
    {
        "id": 239,
        "timestamp": 82.23,
        "hit_pos": 9,
        "hold_pos": 5,
        "note_width": [
            9,
            10,
            11
        ],
        "description": "tap",
        "command": "tap",
        "hitline": 0,
        "execution": "t"
    },
    {
        "id": 240,
        "timestamp": 82.662,
        "hit_pos": 4,
        "hold_pos": 1,
        "note_width": [
            3,
            4,
            5
        ],
        "description": "tap",
        "command": "tap",
        "hitline": 0,
        "execution": "t"
    },
    {
        "id": 241,
        "timestamp": 82.878,
        "hit_pos": 7,
        "hold_pos": 3,
        "note_width": [
            6,
            7,
            8
        ],
        "description": "s_start",
        "command": "tap",
        "hitline": 0,
        "execution": "t"
    },
    {
        "id": 242,
        "timestamp": 83.309,
        "hit_pos": 9,
        "hold_pos": 5,
        "note_width": [
            9,
            10,
            11
        ],
        "description": "s_end",
        "command": "virtual_release",
        "hitline": 2,
        "execution": "r"
    },
    {
        "id": 242.5,
        "timestamp": 83.349,
        "hit_pos": -1,
        "hold_pos": 5,
        "note_width": [],
        "description": "",
        "command": "virtual_resume",
        "hitline": 1,
        "execution": "h"
    },
    {
        "id": 243,
        "timestamp": 83.525,
        "hit_pos": 4,
        "hold_pos": 1,
        "note_width": [
            3,
            4,
            5
        ],
        "description": "tap",
        "command": "tap",
        "hitline": 0,
        "execution": "t"
    },
    {
        "id": 244,
        "timestamp": 83.957,
        "hit_pos": 7,
        "hold_pos": 3,
        "note_width": [
            6,
            7,
            8
        ],
        "description": "tap",
        "command": "tap",
        "hitline": 0,
        "execution": "t"
    },
    {
        "id": 245,
        "timestamp": 84.173,
        "hit_pos": 4,
        "hold_pos": 2,
        "note_width": [
            3,
            4,
            5
        ],
        "description": "tap",
        "command": "tap",
        "hitline": 0,
        "execution": "t"
    },
    {
        "id": 246,
        "timestamp": 84.388,
        "hit_pos": 1,
        "hold_pos": 0,
        "note_width": [
            0,
            1,
            2
        ],
        "description": "tap",
        "command": "tap",
        "hitline": 0,
        "execution": "t"
    },
    {
        "id": 247,
        "timestamp": 84.604,
        "hit_pos": 7,
        "hold_pos": 3,
        "note_width": [
            6,
            7,
            8
        ],
        "description": "s_start",
        "command": "tap",
        "hitline": 0,
        "execution": "t"
    },
    {
        "id": 248,
        "timestamp": 85.468,
        "hit_pos": 9,
        "hold_pos": 5,
        "note_width": [
            9,
            10,
            11
        ],
        "description": "s_end",
        "command": "virtual_release",
        "hitline": 1,
        "execution": "r"
    },
    {
        "id": 248.5,
        "timestamp": 85.50800000000001,
        "hit_pos": -1,
        "hold_pos": 5,
        "note_width": [],
        "description": "",
        "command": "virtual_resume",
        "hitline": 2,
        "execution": "h"
    },
    {
        "id": 249,
        "timestamp": 85.683,
        "hit_pos": 1,
        "hold_pos": 0,
        "note_width": [
            0,
            1,
            2
        ],
        "description": "tap",
        "command": "tap",
        "hitline": 0,
        "execution": "t"
    },
    {
        "id": 250,
        "timestamp": 85.899,
        "hit_pos": 1,
        "hold_pos": 0,
        "note_width": [
            0,
            1,
            2
        ],
        "description": "tap",
        "command": "tap",
        "hitline": 0,
        "execution": "t"
    },
    {
        "id": 251,
        "timestamp": 86.115,
        "hit_pos": 7,
        "hold_pos": 3,
        "note_width": [
            6,
            7,
            8
        ],
        "description": "tap",
        "command": "tap",
        "hitline": 0,
        "execution": "t"
    },
    {
        "id": 252,
        "timestamp": 86.331,
        "hit_pos": 4,
        "hold_pos": 1,
        "note_width": [
            3,
            4,
            5
        ],
        "description": "s_start",
        "command": "tap",
        "hitline": 0,
        "execution": "t"
    },
    {
        "id": 254,
        "timestamp": 87.194,
        "hit_pos": 4,
        "hold_pos": 1,
        "note_width": [
            3,
            4,
            5
        ],
        "description": "s_end",
        "command": "virtual_release",
        "hitline": 2,
        "execution": "r"
    },
    {
        "id": 254.5,
        "timestamp": 87.23400000000001,
        "hit_pos": -1,
        "hold_pos": 1,
        "note_width": [],
        "description": "",
        "command": "virtual_resume",
        "hitline": 1,
        "execution": "h"
    },
    {
        "id": 255,
        "timestamp": 87.41,
        "hit_pos": 7,
        "hold_pos": 3,
        "note_width": [
            6,
            7,
            8
        ],
        "description": "tap",
        "command": "tap",
        "hitline": 0,
        "execution": "t"
    },
    {
        "id": 256,
        "timestamp": 87.626,
        "hit_pos": 4,
        "hold_pos": 2,
        "note_width": [
            3,
            4,
            5
        ],
        "description": "tap",
        "command": "tap",
        "hitline": 0,
        "execution": "t"
    },
    {
        "id": 257,
        "timestamp": 87.842,
        "hit_pos": 7,
        "hold_pos": 3,
        "note_width": [
            6,
            7,
            8
        ],
        "description": "s_start",
        "command": "tap",
        "hitline": 0,
        "execution": "t"
    },
    {
        "id": 258,
        "timestamp": 88.319,
        "hit_pos": 9,
        "hold_pos": 5,
        "note_width": [
            9,
            10,
            11
        ],
        "description": "s_endfl_up",
        "command": "endflick",
        "hitline": 0,
        "execution": "f"
    },
    {
        "id": 259,
        "timestamp": 88.705,
        "hit_pos": 1,
        "hold_pos": 0,
        "note_width": [
            0,
            1,
            2
        ],
        "description": "tap",
        "command": "tap",
        "hitline": 0,
        "execution": "t"
    },
    {
        "id": 260,
        "timestamp": 88.921,
        "hit_pos": 7,
        "hold_pos": 3,
        "note_width": [
            6,
            7,
            8
        ],
        "description": "tap",
        "command": "tap",
        "hitline": 0,
        "execution": "t"
    },
    {
        "id": 261,
        "timestamp": 89.137,
        "hit_pos": 4,
        "hold_pos": 2,
        "note_width": [
            3,
            4,
            5
        ],
        "description": "tap",
        "command": "tap",
        "hitline": 0,
        "execution": "t"
    },
    {
        "id": 262,
        "timestamp": 89.353,
        "hit_pos": 9,
        "hold_pos": 5,
        "note_width": [
            9,
            10,
            11
        ],
        "description": "tap",
        "command": "tap",
        "hitline": 0,
        "execution": "t"
    },
    {
        "id": 263,
        "timestamp": 89.568,
        "hit_pos": 1,
        "hold_pos": 0,
        "note_width": [
            0,
            1,
            2
        ],
        "description": "tap",
        "command": "tap",
        "hitline": 0,
        "execution": "t"
    },
    {
        "id": 264,
        "timestamp": 89.784,
        "hit_pos": 7,
        "hold_pos": 3,
        "note_width": [
            6,
            7,
            8
        ],
        "description": "s_start",
        "command": "tap",
        "hitline": 0,
        "execution": "t"
    },
    {
        "id": 280,
        "timestamp": 91.557,
        "hit_pos": 6,
        "hold_pos": 5,
        "note_width": [
            3,
            4,
            5,
            6,
            7,
            8,
            9,
            10,
            11
        ],
        "description": "s_endfl_up",
        "command": "endflick",
        "hitline": 0,
        "execution": "f"
    },
    {
        "id": 281,
        "timestamp": 92.812,
        "hit_pos": 2,
        "hold_pos": 0,
        "note_width": [
            0,
            1,
            2,
            3
        ],
        "description": "c_c_tapfl_up",
        "command": "flick",
        "hitline": 0,
        "execution": "f"
    },
    {
        "id": 282,
        "timestamp": 92.812,
        "hit_pos": 9,
        "hold_pos": 4,
        "note_width": [
            8,
            9,
            10,
            11
        ],
        "description": "c_c_tapfl_up",
        "command": "flick",
        "hitline": 0,
        "execution": "f"
    },
    {
        "id": 283,
        "timestamp": 93.237,
        "hit_pos": 5,
        "hold_pos": 2,
        "note_width": [
            4,
            5,
            6,
            7
        ],
        "description": "s_start",
        "command": "tap",
        "hitline": 0,
        "execution": "t"
    },
    {
        "id": 291,
        "timestamp": 94.964,
        "hit_pos": 5,
        "hold_pos": 3,
        "note_width": [
            4,
            5,
            6,
            7
        ],
        "description": "s_end",
        "command": "virtual_release",
        "hitline": 2,
        "execution": "r"
    },
    {
        "id": 291.5,
        "timestamp": 95.004,
        "hit_pos": -1,
        "hold_pos": 3,
        "note_width": [],
        "description": "",
        "command": "virtual_resume",
        "hitline": 1,
        "execution": "h"
    },
    {
        "id": 292,
        "timestamp": 96.475,
        "hit_pos": 9,
        "hold_pos": 4,
        "note_width": [
            9,
            10,
            11
        ],
        "description": "c_tap",
        "command": "tap",
        "hitline": 0,
        "execution": "t"
    },
    {
        "id": 293,
        "timestamp": 96.691,
        "hit_pos": 4,
        "hold_pos": 2,
        "note_width": [
            3,
            4,
            5
        ],
        "description": "s_start",
        "command": "tap",
        "hitline": 0,
        "execution": "t"
    },
    {
        "id": 294,
        "timestamp": 97.554,
        "hit_pos": 1,
        "hold_pos": 0,
        "note_width": [
            0,
            1,
            2
        ],
        "description": "s_end",
        "command": "virtual_release",
        "hitline": 1,
        "execution": "r"
    },
    {
        "id": 294.5,
        "timestamp": 97.59400000000001,
        "hit_pos": -1,
        "hold_pos": 0,
        "note_width": [],
        "description": "",
        "command": "virtual_resume",
        "hitline": 2,
        "execution": "h"
    },
    {
        "id": 295,
        "timestamp": 97.77,
        "hit_pos": 9,
        "hold_pos": 5,
        "note_width": [
            9,
            10,
            11
        ],
        "description": "c_tap",
        "command": "tap",
        "hitline": 0,
        "execution": "t"
    },
    {
        "id": 296,
        "timestamp": 97.986,
        "hit_pos": 7,
        "hold_pos": 3,
        "note_width": [
            6,
            7,
            8
        ],
        "description": "c_tap",
        "command": "tap",
        "hitline": 0,
        "execution": "t"
    },
    {
        "id": 297,
        "timestamp": 98.201,
        "hit_pos": 4,
        "hold_pos": 2,
        "note_width": [
            3,
            4,
            5
        ],
        "description": "c_tap",
        "command": "tap",
        "hitline": 0,
        "execution": "t"
    },
    {
        "id": 298,
        "timestamp": 98.417,
        "hit_pos": 7,
        "hold_pos": 3,
        "note_width": [
            6,
            7,
            8
        ],
        "description": "s_start",
        "command": "tap",
        "hitline": 0,
        "execution": "t"
    },
    {
        "id": 299,
        "timestamp": 99.712,
        "hit_pos": 9,
        "hold_pos": 5,
        "note_width": [
            9,
            10,
            11
        ],
        "description": "s_end",
        "command": "virtual_release",
        "hitline": 2,
        "execution": "r"
    },
    {
        "id": 299.5,
        "timestamp": 99.75200000000001,
        "hit_pos": -1,
        "hold_pos": 5,
        "note_width": [],
        "description": "",
        "command": "virtual_resume",
        "hitline": 1,
        "execution": "h"
    },
    {
        "id": 300,
        "timestamp": 100.144,
        "hit_pos": 1,
        "hold_pos": 0,
        "note_width": [
            0,
            1,
            2
        ],
        "description": "s_start",
        "command": "tap",
        "hitline": 0,
        "execution": "t"
    },
    {
        "id": 302,
        "timestamp": 101.439,
        "hit_pos": 1,
        "hold_pos": 0,
        "note_width": [
            0,
            1,
            2
        ],
        "description": "s_end",
        "command": "virtual_release",
        "hitline": 2,
        "execution": "r"
    },
    {
        "id": 302.5,
        "timestamp": 101.479,
        "hit_pos": -1,
        "hold_pos": 0,
        "note_width": [],
        "description": "",
        "command": "virtual_resume",
        "hitline": 1,
        "execution": "h"
    },
    {
        "id": 303,
        "timestamp": 101.871,
        "hit_pos": 7,
        "hold_pos": 3,
        "note_width": [
            6,
            7,
            8
        ],
        "description": "s_start",
        "command": "tap",
        "hitline": 0,
        "execution": "t"
    },
    {
        "id": 305,
        "timestamp": 103.165,
        "hit_pos": 7,
        "hold_pos": 4,
        "note_width": [
            6,
            7,
            8
        ],
        "description": "s_end",
        "command": "virtual_release",
        "hitline": 2,
        "execution": "r"
    },
    {
        "id": 305.5,
        "timestamp": 103.20500000000001,
        "hit_pos": -1,
        "hold_pos": 4,
        "note_width": [],
        "description": "",
        "command": "virtual_resume",
        "hitline": 1,
        "execution": "h"
    },
    {
        "id": 306,
        "timestamp": 103.597,
        "hit_pos": 2,
        "hold_pos": 0,
        "note_width": [
            0,
            1,
            2,
            3
        ],
        "description": "c_tap",
        "command": "tap",
        "hitline": 0,
        "execution": "t"
    },
    {
        "id": 307,
        "timestamp": 104.029,
        "hit_pos": 3,
        "hold_pos": 1,
        "note_width": [
            2,
            3,
            4,
            5
        ],
        "description": "c_tap",
        "command": "tap",
        "hitline": 0,
        "execution": "t"
    },
    {
        "id": 308,
        "timestamp": 104.46,
        "hit_pos": 5,
        "hold_pos": 2,
        "note_width": [
            4,
            5,
            6,
            7
        ],
        "description": "c_tap",
        "command": "tap",
        "hitline": 0,
        "execution": "t"
    },
    {
        "id": 309,
        "timestamp": 104.892,
        "hit_pos": 7,
        "hold_pos": 3,
        "note_width": [
            6,
            7,
            8,
            9
        ],
        "description": "c_tap",
        "command": "tap",
        "hitline": 0,
        "execution": "t"
    },
    {
        "id": 310,
        "timestamp": 105.33,
        "hit_pos": 2,
        "hold_pos": 0,
        "note_width": [
            0,
            1,
            2,
            3
        ],
        "description": "c_c_tapfl_up",
        "command": "flick",
        "hitline": 0,
        "execution": "f"
    },
    {
        "id": 311,
        "timestamp": 105.33,
        "hit_pos": 9,
        "hold_pos": 4,
        "note_width": [
            8,
            9,
            10,
            11
        ],
        "description": "c_c_tapfl_up",
        "command": "flick",
        "hitline": 0,
        "execution": "f"
    },
    {
        "id": 312,
        "timestamp": 106.619,
        "hit_pos": 5,
        "hold_pos": 3,
        "note_width": [
            4,
            5,
            6,
            7
        ],
        "description": "c_tap",
        "command": "tap",
        "hitline": 0,
        "execution": "t"
    },
    {
        "id": 313,
        "timestamp": 107.05,
        "hit_pos": 9,
        "hold_pos": 4,
        "note_width": [
            9,
            10,
            11
        ],
        "description": "c_tap",
        "command": "tap",
        "hitline": 0,
        "execution": "t"
    },
    {
        "id": 314,
        "timestamp": 107.266,
        "hit_pos": 1,
        "hold_pos": 0,
        "note_width": [
            0,
            1,
            2
        ],
        "description": "c_tap",
        "command": "tap",
        "hitline": 0,
        "execution": "t"
    },
    {
        "id": 318,
        "timestamp": 107.914,
        "hit_pos": 1,
        "hold_pos": 0,
        "note_width": [
            0,
            1,
            2
        ],
        "description": "c_tap",
        "command": "tap",
        "hitline": 0,
        "execution": "t"
    },
    {
        "id": 319,
        "timestamp": 108.129,
        "hit_pos": 4,
        "hold_pos": 1,
        "note_width": [
            3,
            4,
            5
        ],
        "description": "c_tap",
        "command": "tap",
        "hitline": 0,
        "execution": "t"
    },
    {
        "id": 320,
        "timestamp": 108.345,
        "hit_pos": 9,
        "hold_pos": 5,
        "note_width": [
            9,
            10,
            11
        ],
        "description": "c_tap",
        "command": "tap",
        "hitline": 0,
        "execution": "t"
    },
    {
        "id": 321,
        "timestamp": 108.561,
        "hit_pos": 7,
        "hold_pos": 3,
        "note_width": [
            6,
            7,
            8
        ],
        "description": "c_tap",
        "command": "tap",
        "hitline": 0,
        "execution": "t"
    },
    {
        "id": 322,
        "timestamp": 108.777,
        "hit_pos": 4,
        "hold_pos": 2,
        "note_width": [
            3,
            4,
            5
        ],
        "description": "s_start",
        "command": "tap",
        "hitline": 0,
        "execution": "t"
    },
    {
        "id": 323,
        "timestamp": 110.072,
        "hit_pos": 1,
        "hold_pos": 0,
        "note_width": [
            0,
            1,
            2
        ],
        "description": "s_end",
        "command": "virtual_release",
        "hitline": 1,
        "execution": "r"
    },
    {
        "id": 323.5,
        "timestamp": 110.11200000000001,
        "hit_pos": -1,
        "hold_pos": 0,
        "note_width": [],
        "description": "",
        "command": "virtual_resume",
        "hitline": 2,
        "execution": "h"
    },
    {
        "id": 324,
        "timestamp": 110.504,
        "hit_pos": 2,
        "hold_pos": 1,
        "note_width": [
            0,
            1,
            2,
            3
        ],
        "description": "s_start",
        "command": "tap",
        "hitline": 0,
        "execution": "t"
    },
    {
        "id": 325,
        "timestamp": 110.504,
        "hit_pos": 9,
        "hold_pos": 5,
        "note_width": [
            8,
            9,
            10,
            11
        ],
        "description": "s_start",
        "command": "tap",
        "hitline": 0,
        "execution": "t"
    }
]